{
  "sower": "NNGGG",
  "seedy": "NGNYN",
  "spend": "NYNNN",
  "surer": "NNNGG",
  "sever": "NGNGG",
  "sheen": "YYNGN",
  "siren": "NNNGY",
  "sweep": "NYYGN",
  "shied": "YNNGN",
  "speck": "NYNNN",
  "sheik": "YYNNN",
  "seven": "NGNGN",
  "serum": "NGNNY",
  "sneer": "NYNGG",
  "super": "NNNGG",
  "speed": "NYNGN",
  "shrew": "YNYGY",
  "sober": "NNNGG",
  "semen": "NGNGN",
  "screw": "NNYGY",
  "sewer": "NGGGG",
  "sperm": "NYNNY",
  "sheer": "YYNGG",
  "sinew": "NNYGN",
  "skier": "NNNGG",
  "sheep": "YYNGN",
  "serif": "NGNNY",
  "spied": "NNNGN"
}